argo_proxy-2.8.2.dist-info/licenses/LICENSE
argoproxy/__init__.py
argoproxy/app.py
argoproxy/cli.py
argoproxy/config.py
argoproxy/models.py
argoproxy/performance.py
argoproxy/py.typed
argoproxy/endpoints/chat.py
argoproxy/endpoints/completions.py
argoproxy/endpoints/embed.py
argoproxy/endpoints/extras.py
argoproxy/endpoints/native_openai.py
argoproxy/endpoints/responses.py
argoproxy/tool_calls/converters.py
argoproxy/tool_calls/deprecated.py
argoproxy/tool_calls/google_helpers.py
argoproxy/tool_calls/handler.py
argoproxy/tool_calls/input_handle.py
argoproxy/tool_calls/output_handle.py
argoproxy/tool_calls/tool_prompts.py
argoproxy/types/__init__.py
argoproxy/types/chat_completion.py
argoproxy/types/completions.py
argoproxy/types/embedding.py
argoproxy/types/function_call.py
argoproxy/types/responses.py
argoproxy/utils/image_processing.py
argoproxy/utils/input_handle.py
argoproxy/utils/logging.py
argoproxy/utils/misc.py
argoproxy/utils/models.py
argoproxy/utils/tokens.py
argoproxy/utils/transports.py
argoproxy/utils/usage.py
argo_proxy-2.8.2.dist-info/METADATA
argo_proxy-2.8.2.dist-info/WHEEL
argo_proxy-2.8.2.dist-info/entry_points.txt
argo_proxy-2.8.2.dist-info/top_level.txt
argo_proxy-2.8.2.dist-info/RECORD
