Metadata-Version: 2.4
Name: argo-proxy
Version: 2.8.2
Summary: Proxy server to Argo API, OpenAI format compatible
Author-email: Peng Ding <oaklight@gmx.com>
License-Expression: MIT
Project-URL: Documentation, https://github.com/Oaklight/argo-openai-proxy#readme
Project-URL: Repository, https://github.com/Oaklight/argo-openai-proxy
Project-URL: Issuses, https://github.com/Oaklight/argo-openai-proxy/issues
Classifier: Intended Audience :: Developers
Classifier: Programming Language :: Python :: 3
Classifier: Topic :: Software Development
Classifier: Topic :: Scientific/Engineering :: Artificial Intelligence
Requires-Python: >=3.10
License-File: LICENSE
Requires-Dist: aiohttp>=3.12.2
Requires-Dist: PyYAML>=6.0.2
Requires-Dist: pydantic>=2.11.7
Requires-Dist: tiktoken>=0.9.0
Requires-Dist: tqdm>=4.67.1
Requires-Dist: packaging>=25.0
Requires-Dist: Pillow>=12.0.0
Provides-Extra: dev
Requires-Dist: dotenv>=0.9.9; extra == "dev"
Requires-Dist: openai>=1.79.0; extra == "dev"
Requires-Dist: pyright>=1.1.402; extra == "dev"
Requires-Dist: build>=1.2.2.post1; extra == "dev"
Requires-Dist: twine>=6.1.0; extra == "dev"
Requires-Dist: httpx>=0.28.1; extra == "dev"
Requires-Dist: requests>=2.25.1; extra == "dev"
Provides-Extra: test
Requires-Dist: openai>=1.79.0; extra == "test"
Requires-Dist: python-dotenv>=1.0.0; extra == "test"
Requires-Dist: numpy>=1.24.0; extra == "test"
Requires-Dist: pytest>=7.0.0; extra == "test"
Requires-Dist: pytest-asyncio>=0.21.0; extra == "test"
Provides-Extra: all
Requires-Dist: argo-proxy[dev,test]; extra == "all"
Dynamic: license-file
